{"1":[{"jornada":1,"local":"S.A.D. FUNDACION RAYO VALLECANO \"B\"","visitante":"CLUB POLID. PARLA ESCUELA","equipoLocal_id":"2729561","equipoVisitante_id":"10658642","goles_local":0,"goles_visitante":0,"fecha":"2019-10-05","hora_prevista":"15:30:00","estado_partido":0,"observaciones":"","codigo_acta":0,"grupo_id":"11435979","estado":0},{"jornada":1,"local":"MADRID C.F. FEMENINO \"C\"","visitante":"A.D. VILLAVICIOSA DE ODON","equipoLocal_id":"10659400","equipoVisitante_id":"10659189","goles_local":0,"goles_visitante":0,"fecha":"2019-10-30","hora_prevista":"20:00:00","estado_partido":0,"observaciones":"","codigo_acta":0,"grupo_id":"11435979","estado":0},{"jornada":1,"local":"A.D. LA MECA DE RIVAS","visitante":"C.D. FUTBOL FEMENINO OLYMPIA LAS ROZAS \"B\"","equipoLocal_id":"10659167","equipoVisitante_id":"10932705","goles_local":0,"goles_visitante":0,"fecha":"2019-10-06","hora_prevista":"13:00:00","estado_partido":0,"observaciones":"","codigo_acta":0,"grupo_id":"11435979","estado":0},{"jornada":1,"local":"ESCUELA DE FUTBOL A.F.E. \"B\"","visitante":"A.D. FUTBOL SALA CHINCHON","equipoLocal_id":"6818319","equipoVisitante_id":"4942038","goles_local":0,"goles_visitante":0,"fecha":"2019-10-05","hora_prevista":"09:00:00","estado_partido":0,"observaciones":"","codigo_acta":0,"grupo_id":"11435979","estado":0},{"jornada":1,"local":"E.F. CIUDAD DE GETAFE","visitante":"C.D. ESC.FUT. VILLA DE MADRID","equipoLocal_id":"10710455","equipoVisitante_id":"10761521","goles_local":0,"goles_visitante":0,"fecha":"2019-10-06","hora_prevista":"11:15:00","estado_partido":0,"observaciones":"","codigo_acta":0,"grupo_id":"11435979","estado":0},{"jornada":1,"local":"FEPE GETAFE III","visitante":"C.D. LIBERTAD ALCORCON","equipoLocal_id":"10652841","equipoVisitante_id":"8947854","goles_local":0,"goles_visitante":0,"fecha":"2019-10-06","hora_prevista":"11:15:00","estado_partido":0,"observaciones":"","codigo_acta":0,"grupo_id":"11435979","estado":0},{"jornada":1,"local":"C.F. FUENLABRADA S.A.D.","visitante":"C.D. RACING CALYPSO","equipoLocal_id":"4931602","equipoVisitante_id":"10946043","goles_local":0,"goles_visitante":0,"fecha":"2019-10-06","hora_prevista":"15:00:00","estado_partido":0,"observaciones":"","codigo_acta":0,"grupo_id":"11435979","estado":0},{"jornada":1,"local":"C.D. COLONIA MOSCARDO","visitante":"C.D.C. CIEMPOZUELOS","equipoLocal_id":"8929864","equipoVisitante_id":"6818240","goles_local":0,"goles_visitante":0,"fecha":"2019-10-30","hora_prevista":"19:45:00","estado_partido":0,"observaciones":"","codigo_acta":0,"grupo_id":"11435979","estado":0}],"2":[{"jornada":2,"local":"CLUB POLID. PARLA ESCUELA","visitante":"C.D. COLONIA MOSCARDO","equipoLocal_id":"10658642","equipoVisitante_id":"8929864","goles_local":0,"goles_visitante":0,"fecha":"2019-10-13","hora_prevista":"19:30:00","estado_partido":0,"observaciones":"","codigo_acta":0,"grupo_id":"11435979","estado":0},{"jornada":2,"local":"A.D. VILLAVICIOSA DE ODON","visitante":"S.A.D. FUNDACION RAYO VALLECANO \"B\"","equipoLocal_id":"10659189","equipoVisitante_id":"2729561","goles_local":0,"goles_visitante":0,"fecha":"2019-10-13","hora_prevista":"00:00:00","estado_partido":0,"observaciones":"","codigo_acta":0,"grupo_id":"11435979","estado":0},{"jornada":2,"local":"C.D. FUTBOL FEMENINO OLYMPIA LAS ROZAS \"B\"","visitante":"MADRID C.F. FEMENINO \"C\"","equipoLocal_id":"10932705","equipoVisitante_id":"10659400","goles_local":0,"goles_visitante":0,"fecha":"2019-10-12","hora_prevista":"18:30:00","estado_partido":0,"observaciones":"","codigo_acta":0,"grupo_id":"11435979","estado":0},{"jornada":2,"local":"A.D. FUTBOL SALA CHINCHON","visitante":"A.D. LA MECA DE RIVAS","equipoLocal_id":"4942038","equipoVisitante_id":"10659167","goles_local":0,"goles_visitante":0,"fecha":"2019-10-13","hora_prevista":"00:00:00","estado_partido":0,"observaciones":"","codigo_acta":0,"grupo_id":"11435979","estado":0},{"jornada":2,"local":"C.D. ESC.FUT. VILLA DE MADRID","visitante":"ESCUELA DE FUTBOL A.F.E. \"B\"","equipoLocal_id":"10761521","equipoVisitante_id":"6818319","goles_local":0,"goles_visitante":0,"fecha":"2019-10-13","hora_prevista":"00:00:00","estado_partido":0,"observaciones":"","codigo_acta":0,"grupo_id":"11435979","estado":0},{"jornada":2,"local":"C.D. LIBERTAD ALCORCON","visitante":"E.F. CIUDAD DE GETAFE","equipoLocal_id":"8947854","equipoVisitante_id":"10710455","goles_local":0,"goles_visitante":0,"fecha":"2019-10-13","hora_prevista":"00:00:00","estado_partido":0,"observaciones":"","codigo_acta":0,"grupo_id":"11435979","estado":0},{"jornada":2,"local":"C.D. RACING CALYPSO","visitante":"FEPE GETAFE III","equipoLocal_id":"10946043","equipoVisitante_id":"10652841","goles_local":0,"goles_visitante":0,"fecha":"2019-10-12","hora_prevista":"19:00:00","estado_partido":0,"observaciones":"","codigo_acta":0,"grupo_id":"11435979","estado":0},{"jornada":2,"local":"C.D.C. CIEMPOZUELOS","visitante":"C.F. FUENLABRADA S.A.D.","equipoLocal_id":"6818240","equipoVisitante_id":"4931602","goles_local":0,"goles_visitante":0,"fecha":"2019-10-13","hora_prevista":"00:00:00","estado_partido":0,"observaciones":"","codigo_acta":0,"grupo_id":"11435979","estado":0}],"3":[{"jornada":3,"local":"CLUB POLID. PARLA ESCUELA","visitante":"A.D. VILLAVICIOSA DE ODON","equipoLocal_id":"10658642","equipoVisitante_id":"10659189","goles_local":0,"goles_visitante":0,"fecha":"2019-10-20","hora_prevista":"19:30:00","estado_partido":0,"observaciones":"","codigo_acta":0,"grupo_id":"11435979","estado":0},{"jornada":3,"local":"S.A.D. FUNDACION RAYO VALLECANO \"B\"","visitante":"C.D. FUTBOL FEMENINO OLYMPIA LAS ROZAS \"B\"","equipoLocal_id":"2729561","equipoVisitante_id":"10932705","goles_local":0,"goles_visitante":0,"fecha":"2019-10-20","hora_prevista":"00:00:00","estado_partido":0,"observaciones":"","codigo_acta":0,"grupo_id":"11435979","estado":0},{"jornada":3,"local":"MADRID C.F. FEMENINO \"C\"","visitante":"A.D. FUTBOL SALA CHINCHON","equipoLocal_id":"10659400","equipoVisitante_id":"4942038","goles_local":0,"goles_visitante":0,"fecha":"2019-10-20","hora_prevista":"00:00:00","estado_partido":0,"observaciones":"","codigo_acta":0,"grupo_id":"11435979","estado":0},{"jornada":3,"local":"A.D. LA MECA DE RIVAS","visitante":"C.D. ESC.FUT. VILLA DE MADRID","equipoLocal_id":"10659167","equipoVisitante_id":"10761521","goles_local":0,"goles_visitante":0,"fecha":"2019-10-20","hora_prevista":"00:00:00","estado_partido":0,"observaciones":"","codigo_acta":0,"grupo_id":"11435979","estado":0},{"jornada":3,"local":"ESCUELA DE FUTBOL A.F.E. \"B\"","visitante":"C.D. LIBERTAD ALCORCON","equipoLocal_id":"6818319","equipoVisitante_id":"8947854","goles_local":0,"goles_visitante":0,"fecha":"2019-10-20","hora_prevista":"00:00:00","estado_partido":0,"observaciones":"","codigo_acta":0,"grupo_id":"11435979","estado":0},{"jornada":3,"local":"E.F. CIUDAD DE GETAFE","visitante":"C.D. RACING CALYPSO","equipoLocal_id":"10710455","equipoVisitante_id":"10946043","goles_local":0,"goles_visitante":0,"fecha":"2019-10-20","hora_prevista":"00:00:00","estado_partido":0,"observaciones":"","codigo_acta":0,"grupo_id":"11435979","estado":0},{"jornada":3,"local":"FEPE GETAFE III","visitante":"C.D.C. CIEMPOZUELOS","equipoLocal_id":"10652841","equipoVisitante_id":"6818240","goles_local":0,"goles_visitante":0,"fecha":"2019-10-20","hora_prevista":"00:00:00","estado_partido":0,"observaciones":"","codigo_acta":0,"grupo_id":"11435979","estado":0},{"jornada":3,"local":"C.D. COLONIA MOSCARDO","visitante":"C.F. FUENLABRADA S.A.D.","equipoLocal_id":"8929864","equipoVisitante_id":"4931602","goles_local":0,"goles_visitante":0,"fecha":"2019-10-20","hora_prevista":"00:00:00","estado_partido":0,"observaciones":"","codigo_acta":0,"grupo_id":"11435979","estado":0}],"4":[{"jornada":4,"local":"A.D. VILLAVICIOSA DE ODON","visitante":"C.D. COLONIA MOSCARDO","equipoLocal_id":"10659189","equipoVisitante_id":"8929864","goles_local":0,"goles_visitante":0,"fecha":"2019-10-27","hora_prevista":"00:00:00","estado_partido":0,"observaciones":"","codigo_acta":0,"grupo_id":"11435979","estado":0},{"jornada":4,"local":"C.D. FUTBOL FEMENINO OLYMPIA LAS ROZAS \"B\"","visitante":"CLUB POLID. PARLA ESCUELA","equipoLocal_id":"10932705","equipoVisitante_id":"10658642","goles_local":0,"goles_visitante":0,"fecha":"2019-10-27","hora_prevista":"00:00:00","estado_partido":0,"observaciones":"","codigo_acta":0,"grupo_id":"11435979","estado":0},{"jornada":4,"local":"A.D. FUTBOL SALA CHINCHON","visitante":"S.A.D. FUNDACION RAYO VALLECANO \"B\"","equipoLocal_id":"4942038","equipoVisitante_id":"2729561","goles_local":0,"goles_visitante":0,"fecha":"2019-10-27","hora_prevista":"00:00:00","estado_partido":0,"observaciones":"","codigo_acta":0,"grupo_id":"11435979","estado":0},{"jornada":4,"local":"C.D. ESC.FUT. VILLA DE MADRID","visitante":"MADRID C.F. FEMENINO \"C\"","equipoLocal_id":"10761521","equipoVisitante_id":"10659400","goles_local":0,"goles_visitante":0,"fecha":"2019-10-27","hora_prevista":"00:00:00","estado_partido":0,"observaciones":"","codigo_acta":0,"grupo_id":"11435979","estado":0},{"jornada":4,"local":"C.D. LIBERTAD ALCORCON","visitante":"A.D. LA MECA DE RIVAS","equipoLocal_id":"8947854","equipoVisitante_id":"10659167","goles_local":0,"goles_visitante":0,"fecha":"2019-10-27","hora_prevista":"00:00:00","estado_partido":0,"observaciones":"","codigo_acta":0,"grupo_id":"11435979","estado":0},{"jornada":4,"local":"C.D. RACING CALYPSO","visitante":"ESCUELA DE FUTBOL A.F.E. \"B\"","equipoLocal_id":"10946043","equipoVisitante_id":"6818319","goles_local":0,"goles_visitante":0,"fecha":"2019-10-27","hora_prevista":"00:00:00","estado_partido":0,"observaciones":"","codigo_acta":0,"grupo_id":"11435979","estado":0},{"jornada":4,"local":"C.D.C. CIEMPOZUELOS","visitante":"E.F. CIUDAD DE GETAFE","equipoLocal_id":"6818240","equipoVisitante_id":"10710455","goles_local":0,"goles_visitante":0,"fecha":"2019-10-27","hora_prevista":"00:00:00","estado_partido":0,"observaciones":"","codigo_acta":0,"grupo_id":"11435979","estado":0},{"jornada":4,"local":"C.F. FUENLABRADA S.A.D.","visitante":"FEPE GETAFE III","equipoLocal_id":"4931602","equipoVisitante_id":"10652841","goles_local":0,"goles_visitante":0,"fecha":"2019-10-27","hora_prevista":"00:00:00","estado_partido":0,"observaciones":"","codigo_acta":0,"grupo_id":"11435979","estado":0}],"5":[{"jornada":5,"local":"A.D. VILLAVICIOSA DE ODON","visitante":"C.D. FUTBOL FEMENINO OLYMPIA LAS ROZAS \"B\"","equipoLocal_id":"10659189","equipoVisitante_id":"10932705","goles_local":0,"goles_visitante":0,"fecha":"2019-11-03","hora_prevista":"00:00:00","estado_partido":0,"observaciones":"","codigo_acta":0,"grupo_id":"11435979","estado":0},{"jornada":5,"local":"CLUB POLID. PARLA ESCUELA","visitante":"A.D. FUTBOL SALA CHINCHON","equipoLocal_id":"10658642","equipoVisitante_id":"4942038","goles_local":0,"goles_visitante":0,"fecha":"2019-11-03","hora_prevista":"00:00:00","estado_partido":0,"observaciones":"","codigo_acta":0,"grupo_id":"11435979","estado":0},{"jornada":5,"local":"S.A.D. FUNDACION RAYO VALLECANO \"B\"","visitante":"C.D. ESC.FUT. VILLA DE MADRID","equipoLocal_id":"2729561","equipoVisitante_id":"10761521","goles_local":0,"goles_visitante":0,"fecha":"2019-11-03","hora_prevista":"00:00:00","estado_partido":0,"observaciones":"","codigo_acta":0,"grupo_id":"11435979","estado":0},{"jornada":5,"local":"MADRID C.F. FEMENINO \"C\"","visitante":"C.D. LIBERTAD ALCORCON","equipoLocal_id":"10659400","equipoVisitante_id":"8947854","goles_local":0,"goles_visitante":0,"fecha":"2019-11-03","hora_prevista":"00:00:00","estado_partido":0,"observaciones":"","codigo_acta":0,"grupo_id":"11435979","estado":0},{"jornada":5,"local":"A.D. LA MECA DE RIVAS","visitante":"C.D. RACING CALYPSO","equipoLocal_id":"10659167","equipoVisitante_id":"10946043","goles_local":0,"goles_visitante":0,"fecha":"2019-11-03","hora_prevista":"00:00:00","estado_partido":0,"observaciones":"","codigo_acta":0,"grupo_id":"11435979","estado":0},{"jornada":5,"local":"ESCUELA DE FUTBOL A.F.E. \"B\"","visitante":"C.D.C. CIEMPOZUELOS","equipoLocal_id":"6818319","equipoVisitante_id":"6818240","goles_local":0,"goles_visitante":0,"fecha":"2019-11-03","hora_prevista":"00:00:00","estado_partido":0,"observaciones":"","codigo_acta":0,"grupo_id":"11435979","estado":0},{"jornada":5,"local":"E.F. CIUDAD DE GETAFE","visitante":"C.F. FUENLABRADA S.A.D.","equipoLocal_id":"10710455","equipoVisitante_id":"4931602","goles_local":0,"goles_visitante":0,"fecha":"2019-11-03","hora_prevista":"00:00:00","estado_partido":0,"observaciones":"","codigo_acta":0,"grupo_id":"11435979","estado":0},{"jornada":5,"local":"C.D. COLONIA MOSCARDO","visitante":"FEPE GETAFE III","equipoLocal_id":"8929864","equipoVisitante_id":"10652841","goles_local":0,"goles_visitante":0,"fecha":"2019-11-03","hora_prevista":"00:00:00","estado_partido":0,"observaciones":"","codigo_acta":0,"grupo_id":"11435979","estado":0}],"6":[{"jornada":6,"local":"C.D. FUTBOL FEMENINO OLYMPIA LAS ROZAS \"B\"","visitante":"C.D. COLONIA MOSCARDO","equipoLocal_id":"10932705","equipoVisitante_id":"8929864","goles_local":0,"goles_visitante":0,"fecha":"2019-11-10","hora_prevista":"00:00:00","estado_partido":0,"observaciones":"","codigo_acta":0,"grupo_id":"11435979","estado":0},{"jornada":6,"local":"A.D. FUTBOL SALA CHINCHON","visitante":"A.D. VILLAVICIOSA DE ODON","equipoLocal_id":"4942038","equipoVisitante_id":"10659189","goles_local":0,"goles_visitante":0,"fecha":"2019-11-10","hora_prevista":"00:00:00","estado_partido":0,"observaciones":"","codigo_acta":0,"grupo_id":"11435979","estado":0},{"jornada":6,"local":"C.D. ESC.FUT. VILLA DE MADRID","visitante":"CLUB POLID. PARLA ESCUELA","equipoLocal_id":"10761521","equipoVisitante_id":"10658642","goles_local":0,"goles_visitante":0,"fecha":"2019-11-10","hora_prevista":"00:00:00","estado_partido":0,"observaciones":"","codigo_acta":0,"grupo_id":"11435979","estado":0},{"jornada":6,"local":"C.D. LIBERTAD ALCORCON","visitante":"S.A.D. FUNDACION RAYO VALLECANO \"B\"","equipoLocal_id":"8947854","equipoVisitante_id":"2729561","goles_local":0,"goles_visitante":0,"fecha":"2019-11-10","hora_prevista":"00:00:00","estado_partido":0,"observaciones":"","codigo_acta":0,"grupo_id":"11435979","estado":0},{"jornada":6,"local":"C.D. RACING CALYPSO","visitante":"MADRID C.F. FEMENINO \"C\"","equipoLocal_id":"10946043","equipoVisitante_id":"10659400","goles_local":0,"goles_visitante":0,"fecha":"2019-11-10","hora_prevista":"00:00:00","estado_partido":0,"observaciones":"","codigo_acta":0,"grupo_id":"11435979","estado":0},{"jornada":6,"local":"C.D.C. CIEMPOZUELOS","visitante":"A.D. LA MECA DE RIVAS","equipoLocal_id":"6818240","equipoVisitante_id":"10659167","goles_local":0,"goles_visitante":0,"fecha":"2019-11-10","hora_prevista":"00:00:00","estado_partido":0,"observaciones":"","codigo_acta":0,"grupo_id":"11435979","estado":0},{"jornada":6,"local":"C.F. FUENLABRADA S.A.D.","visitante":"ESCUELA DE FUTBOL A.F.E. \"B\"","equipoLocal_id":"4931602","equipoVisitante_id":"6818319","goles_local":0,"goles_visitante":0,"fecha":"2019-11-10","hora_prevista":"00:00:00","estado_partido":0,"observaciones":"","codigo_acta":0,"grupo_id":"11435979","estado":0},{"jornada":6,"local":"FEPE GETAFE III","visitante":"E.F. CIUDAD DE GETAFE","equipoLocal_id":"10652841","equipoVisitante_id":"10710455","goles_local":0,"goles_visitante":0,"fecha":"2019-11-10","hora_prevista":"00:00:00","estado_partido":0,"observaciones":"","codigo_acta":0,"grupo_id":"11435979","estado":0}],"7":[{"jornada":7,"local":"C.D. FUTBOL FEMENINO OLYMPIA LAS ROZAS \"B\"","visitante":"A.D. FUTBOL SALA CHINCHON","equipoLocal_id":"10932705","equipoVisitante_id":"4942038","goles_local":0,"goles_visitante":0,"fecha":"2019-11-17","hora_prevista":"00:00:00","estado_partido":0,"observaciones":"","codigo_acta":0,"grupo_id":"11435979","estado":0},{"jornada":7,"local":"A.D. VILLAVICIOSA DE ODON","visitante":"C.D. ESC.FUT. VILLA DE MADRID","equipoLocal_id":"10659189","equipoVisitante_id":"10761521","goles_local":0,"goles_visitante":0,"fecha":"2019-11-17","hora_prevista":"00:00:00","estado_partido":0,"observaciones":"","codigo_acta":0,"grupo_id":"11435979","estado":0},{"jornada":7,"local":"CLUB POLID. PARLA ESCUELA","visitante":"C.D. LIBERTAD ALCORCON","equipoLocal_id":"10658642","equipoVisitante_id":"8947854","goles_local":0,"goles_visitante":0,"fecha":"2019-11-17","hora_prevista":"00:00:00","estado_partido":0,"observaciones":"","codigo_acta":0,"grupo_id":"11435979","estado":0},{"jornada":7,"local":"S.A.D. FUNDACION RAYO VALLECANO \"B\"","visitante":"C.D. RACING CALYPSO","equipoLocal_id":"2729561","equipoVisitante_id":"10946043","goles_local":0,"goles_visitante":0,"fecha":"2019-11-17","hora_prevista":"00:00:00","estado_partido":0,"observaciones":"","codigo_acta":0,"grupo_id":"11435979","estado":0},{"jornada":7,"local":"MADRID C.F. FEMENINO \"C\"","visitante":"C.D.C. CIEMPOZUELOS","equipoLocal_id":"10659400","equipoVisitante_id":"6818240","goles_local":0,"goles_visitante":0,"fecha":"2019-11-17","hora_prevista":"00:00:00","estado_partido":0,"observaciones":"","codigo_acta":0,"grupo_id":"11435979","estado":0},{"jornada":7,"local":"A.D. LA MECA DE RIVAS","visitante":"C.F. FUENLABRADA S.A.D.","equipoLocal_id":"10659167","equipoVisitante_id":"4931602","goles_local":0,"goles_visitante":0,"fecha":"2019-11-17","hora_prevista":"00:00:00","estado_partido":0,"observaciones":"","codigo_acta":0,"grupo_id":"11435979","estado":0},{"jornada":7,"local":"ESCUELA DE FUTBOL A.F.E. \"B\"","visitante":"FEPE GETAFE III","equipoLocal_id":"6818319","equipoVisitante_id":"10652841","goles_local":0,"goles_visitante":0,"fecha":"2019-11-17","hora_prevista":"00:00:00","estado_partido":0,"observaciones":"","codigo_acta":0,"grupo_id":"11435979","estado":0},{"jornada":7,"local":"C.D. COLONIA MOSCARDO","visitante":"E.F. CIUDAD DE GETAFE","equipoLocal_id":"8929864","equipoVisitante_id":"10710455","goles_local":0,"goles_visitante":0,"fecha":"2019-11-17","hora_prevista":"00:00:00","estado_partido":0,"observaciones":"","codigo_acta":0,"grupo_id":"11435979","estado":0}],"8":[{"jornada":8,"local":"A.D. FUTBOL SALA CHINCHON","visitante":"C.D. COLONIA MOSCARDO","equipoLocal_id":"4942038","equipoVisitante_id":"8929864","goles_local":0,"goles_visitante":0,"fecha":"2019-11-24","hora_prevista":"00:00:00","estado_partido":0,"observaciones":"","codigo_acta":0,"grupo_id":"11435979","estado":0},{"jornada":8,"local":"C.D. ESC.FUT. VILLA DE MADRID","visitante":"C.D. FUTBOL FEMENINO OLYMPIA LAS ROZAS \"B\"","equipoLocal_id":"10761521","equipoVisitante_id":"10932705","goles_local":0,"goles_visitante":0,"fecha":"2019-11-24","hora_prevista":"00:00:00","estado_partido":0,"observaciones":"","codigo_acta":0,"grupo_id":"11435979","estado":0},{"jornada":8,"local":"C.D. LIBERTAD ALCORCON","visitante":"A.D. VILLAVICIOSA DE ODON","equipoLocal_id":"8947854","equipoVisitante_id":"10659189","goles_local":0,"goles_visitante":0,"fecha":"2019-11-24","hora_prevista":"00:00:00","estado_partido":0,"observaciones":"","codigo_acta":0,"grupo_id":"11435979","estado":0},{"jornada":8,"local":"C.D. RACING CALYPSO","visitante":"CLUB POLID. PARLA ESCUELA","equipoLocal_id":"10946043","equipoVisitante_id":"10658642","goles_local":0,"goles_visitante":0,"fecha":"2019-11-24","hora_prevista":"00:00:00","estado_partido":0,"observaciones":"","codigo_acta":0,"grupo_id":"11435979","estado":0},{"jornada":8,"local":"C.D.C. CIEMPOZUELOS","visitante":"S.A.D. FUNDACION RAYO VALLECANO \"B\"","equipoLocal_id":"6818240","equipoVisitante_id":"2729561","goles_local":0,"goles_visitante":0,"fecha":"2019-11-24","hora_prevista":"00:00:00","estado_partido":0,"observaciones":"","codigo_acta":0,"grupo_id":"11435979","estado":0},{"jornada":8,"local":"C.F. FUENLABRADA S.A.D.","visitante":"MADRID C.F. FEMENINO \"C\"","equipoLocal_id":"4931602","equipoVisitante_id":"10659400","goles_local":0,"goles_visitante":0,"fecha":"2019-11-24","hora_prevista":"00:00:00","estado_partido":0,"observaciones":"","codigo_acta":0,"grupo_id":"11435979","estado":0},{"jornada":8,"local":"FEPE GETAFE III","visitante":"A.D. LA MECA DE RIVAS","equipoLocal_id":"10652841","equipoVisitante_id":"10659167","goles_local":0,"goles_visitante":0,"fecha":"2019-11-24","hora_prevista":"00:00:00","estado_partido":0,"observaciones":"","codigo_acta":0,"grupo_id":"11435979","estado":0},{"jornada":8,"local":"E.F. CIUDAD DE GETAFE","visitante":"ESCUELA DE FUTBOL A.F.E. \"B\"","equipoLocal_id":"10710455","equipoVisitante_id":"6818319","goles_local":0,"goles_visitante":0,"fecha":"2019-11-24","hora_prevista":"00:00:00","estado_partido":0,"observaciones":"","codigo_acta":0,"grupo_id":"11435979","estado":0}],"9":[{"jornada":9,"local":"A.D. FUTBOL SALA CHINCHON","visitante":"C.D. ESC.FUT. VILLA DE MADRID","equipoLocal_id":"4942038","equipoVisitante_id":"10761521","goles_local":0,"goles_visitante":0,"fecha":"2019-12-01","hora_prevista":"00:00:00","estado_partido":0,"observaciones":"","codigo_acta":0,"grupo_id":"11435979","estado":0},{"jornada":9,"local":"C.D. FUTBOL FEMENINO OLYMPIA LAS ROZAS \"B\"","visitante":"C.D. LIBERTAD ALCORCON","equipoLocal_id":"10932705","equipoVisitante_id":"8947854","goles_local":0,"goles_visitante":0,"fecha":"2019-12-01","hora_prevista":"00:00:00","estado_partido":0,"observaciones":"","codigo_acta":0,"grupo_id":"11435979","estado":0},{"jornada":9,"local":"A.D. VILLAVICIOSA DE ODON","visitante":"C.D. RACING CALYPSO","equipoLocal_id":"10659189","equipoVisitante_id":"10946043","goles_local":0,"goles_visitante":0,"fecha":"2019-12-01","hora_prevista":"00:00:00","estado_partido":0,"observaciones":"","codigo_acta":0,"grupo_id":"11435979","estado":0},{"jornada":9,"local":"CLUB POLID. PARLA ESCUELA","visitante":"C.D.C. CIEMPOZUELOS","equipoLocal_id":"10658642","equipoVisitante_id":"6818240","goles_local":0,"goles_visitante":0,"fecha":"2019-12-01","hora_prevista":"00:00:00","estado_partido":0,"observaciones":"","codigo_acta":0,"grupo_id":"11435979","estado":0},{"jornada":9,"local":"S.A.D. FUNDACION RAYO VALLECANO \"B\"","visitante":"C.F. FUENLABRADA S.A.D.","equipoLocal_id":"2729561","equipoVisitante_id":"4931602","goles_local":0,"goles_visitante":0,"fecha":"2019-12-01","hora_prevista":"00:00:00","estado_partido":0,"observaciones":"","codigo_acta":0,"grupo_id":"11435979","estado":0},{"jornada":9,"local":"MADRID C.F. FEMENINO \"C\"","visitante":"FEPE GETAFE III","equipoLocal_id":"10659400","equipoVisitante_id":"10652841","goles_local":0,"goles_visitante":0,"fecha":"2019-12-01","hora_prevista":"00:00:00","estado_partido":0,"observaciones":"","codigo_acta":0,"grupo_id":"11435979","estado":0},{"jornada":9,"local":"A.D. LA MECA DE RIVAS","visitante":"E.F. CIUDAD DE GETAFE","equipoLocal_id":"10659167","equipoVisitante_id":"10710455","goles_local":0,"goles_visitante":0,"fecha":"2019-12-01","hora_prevista":"00:00:00","estado_partido":0,"observaciones":"","codigo_acta":0,"grupo_id":"11435979","estado":0},{"jornada":9,"local":"C.D. COLONIA MOSCARDO","visitante":"ESCUELA DE FUTBOL A.F.E. \"B\"","equipoLocal_id":"8929864","equipoVisitante_id":"6818319","goles_local":0,"goles_visitante":0,"fecha":"2019-12-01","hora_prevista":"00:00:00","estado_partido":0,"observaciones":"","codigo_acta":0,"grupo_id":"11435979","estado":0}],"10":[{"jornada":10,"local":"C.D. ESC.FUT. VILLA DE MADRID","visitante":"C.D. COLONIA MOSCARDO","equipoLocal_id":"10761521","equipoVisitante_id":"8929864","goles_local":0,"goles_visitante":0,"fecha":"2019-12-15","hora_prevista":"00:00:00","estado_partido":0,"observaciones":"","codigo_acta":0,"grupo_id":"11435979","estado":0},{"jornada":10,"local":"C.D. LIBERTAD ALCORCON","visitante":"A.D. FUTBOL SALA CHINCHON","equipoLocal_id":"8947854","equipoVisitante_id":"4942038","goles_local":0,"goles_visitante":0,"fecha":"2019-12-15","hora_prevista":"00:00:00","estado_partido":0,"observaciones":"","codigo_acta":0,"grupo_id":"11435979","estado":0},{"jornada":10,"local":"C.D. RACING CALYPSO","visitante":"C.D. FUTBOL FEMENINO OLYMPIA LAS ROZAS \"B\"","equipoLocal_id":"10946043","equipoVisitante_id":"10932705","goles_local":0,"goles_visitante":0,"fecha":"2019-12-15","hora_prevista":"00:00:00","estado_partido":0,"observaciones":"","codigo_acta":0,"grupo_id":"11435979","estado":0},{"jornada":10,"local":"C.D.C. CIEMPOZUELOS","visitante":"A.D. VILLAVICIOSA DE ODON","equipoLocal_id":"6818240","equipoVisitante_id":"10659189","goles_local":0,"goles_visitante":0,"fecha":"2019-12-15","hora_prevista":"00:00:00","estado_partido":0,"observaciones":"","codigo_acta":0,"grupo_id":"11435979","estado":0},{"jornada":10,"local":"C.F. FUENLABRADA S.A.D.","visitante":"CLUB POLID. PARLA ESCUELA","equipoLocal_id":"4931602","equipoVisitante_id":"10658642","goles_local":0,"goles_visitante":0,"fecha":"2019-12-15","hora_prevista":"00:00:00","estado_partido":0,"observaciones":"","codigo_acta":0,"grupo_id":"11435979","estado":0},{"jornada":10,"local":"FEPE GETAFE III","visitante":"S.A.D. FUNDACION RAYO VALLECANO \"B\"","equipoLocal_id":"10652841","equipoVisitante_id":"2729561","goles_local":0,"goles_visitante":0,"fecha":"2019-12-15","hora_prevista":"00:00:00","estado_partido":0,"observaciones":"","codigo_acta":0,"grupo_id":"11435979","estado":0},{"jornada":10,"local":"E.F. CIUDAD DE GETAFE","visitante":"MADRID C.F. FEMENINO \"C\"","equipoLocal_id":"10710455","equipoVisitante_id":"10659400","goles_local":0,"goles_visitante":0,"fecha":"2019-12-15","hora_prevista":"00:00:00","estado_partido":0,"observaciones":"","codigo_acta":0,"grupo_id":"11435979","estado":0},{"jornada":10,"local":"ESCUELA DE FUTBOL A.F.E. \"B\"","visitante":"A.D. LA MECA DE RIVAS","equipoLocal_id":"6818319","equipoVisitante_id":"10659167","goles_local":0,"goles_visitante":0,"fecha":"2019-12-15","hora_prevista":"00:00:00","estado_partido":0,"observaciones":"","codigo_acta":0,"grupo_id":"11435979","estado":0}],"11":[{"jornada":11,"local":"C.D. ESC.FUT. VILLA DE MADRID","visitante":"C.D. LIBERTAD ALCORCON","equipoLocal_id":"10761521","equipoVisitante_id":"8947854","goles_local":0,"goles_visitante":0,"fecha":"2019-12-22","hora_prevista":"00:00:00","estado_partido":0,"observaciones":"","codigo_acta":0,"grupo_id":"11435979","estado":0},{"jornada":11,"local":"A.D. FUTBOL SALA CHINCHON","visitante":"C.D. RACING CALYPSO","equipoLocal_id":"4942038","equipoVisitante_id":"10946043","goles_local":0,"goles_visitante":0,"fecha":"2019-12-22","hora_prevista":"00:00:00","estado_partido":0,"observaciones":"","codigo_acta":0,"grupo_id":"11435979","estado":0},{"jornada":11,"local":"C.D. FUTBOL FEMENINO OLYMPIA LAS ROZAS \"B\"","visitante":"C.D.C. CIEMPOZUELOS","equipoLocal_id":"10932705","equipoVisitante_id":"6818240","goles_local":0,"goles_visitante":0,"fecha":"2019-12-22","hora_prevista":"00:00:00","estado_partido":0,"observaciones":"","codigo_acta":0,"grupo_id":"11435979","estado":0},{"jornada":11,"local":"A.D. VILLAVICIOSA DE ODON","visitante":"C.F. FUENLABRADA S.A.D.","equipoLocal_id":"10659189","equipoVisitante_id":"4931602","goles_local":0,"goles_visitante":0,"fecha":"2019-12-22","hora_prevista":"00:00:00","estado_partido":0,"observaciones":"","codigo_acta":0,"grupo_id":"11435979","estado":0},{"jornada":11,"local":"CLUB POLID. PARLA ESCUELA","visitante":"FEPE GETAFE III","equipoLocal_id":"10658642","equipoVisitante_id":"10652841","goles_local":0,"goles_visitante":0,"fecha":"2019-12-22","hora_prevista":"00:00:00","estado_partido":0,"observaciones":"","codigo_acta":0,"grupo_id":"11435979","estado":0},{"jornada":11,"local":"S.A.D. FUNDACION RAYO VALLECANO \"B\"","visitante":"E.F. CIUDAD DE GETAFE","equipoLocal_id":"2729561","equipoVisitante_id":"10710455","goles_local":0,"goles_visitante":0,"fecha":"2019-12-22","hora_prevista":"00:00:00","estado_partido":0,"observaciones":"","codigo_acta":0,"grupo_id":"11435979","estado":0},{"jornada":11,"local":"MADRID C.F. FEMENINO \"C\"","visitante":"ESCUELA DE FUTBOL A.F.E. \"B\"","equipoLocal_id":"10659400","equipoVisitante_id":"6818319","goles_local":0,"goles_visitante":0,"fecha":"2019-12-22","hora_prevista":"00:00:00","estado_partido":0,"observaciones":"","codigo_acta":0,"grupo_id":"11435979","estado":0},{"jornada":11,"local":"C.D. COLONIA MOSCARDO","visitante":"A.D. LA MECA DE RIVAS","equipoLocal_id":"8929864","equipoVisitante_id":"10659167","goles_local":0,"goles_visitante":0,"fecha":"2019-12-22","hora_prevista":"00:00:00","estado_partido":0,"observaciones":"","codigo_acta":0,"grupo_id":"11435979","estado":0}],"12":[{"jornada":12,"local":"C.D. LIBERTAD ALCORCON","visitante":"C.D. COLONIA MOSCARDO","equipoLocal_id":"8947854","equipoVisitante_id":"8929864","goles_local":0,"goles_visitante":0,"fecha":"2020-01-12","hora_prevista":"00:00:00","estado_partido":0,"observaciones":"","codigo_acta":0,"grupo_id":"11435979","estado":0},{"jornada":12,"local":"C.D. RACING CALYPSO","visitante":"C.D. ESC.FUT. VILLA DE MADRID","equipoLocal_id":"10946043","equipoVisitante_id":"10761521","goles_local":0,"goles_visitante":0,"fecha":"2020-01-12","hora_prevista":"00:00:00","estado_partido":0,"observaciones":"","codigo_acta":0,"grupo_id":"11435979","estado":0},{"jornada":12,"local":"C.D.C. CIEMPOZUELOS","visitante":"A.D. FUTBOL SALA CHINCHON","equipoLocal_id":"6818240","equipoVisitante_id":"4942038","goles_local":0,"goles_visitante":0,"fecha":"2020-01-12","hora_prevista":"00:00:00","estado_partido":0,"observaciones":"","codigo_acta":0,"grupo_id":"11435979","estado":0},{"jornada":12,"local":"C.F. FUENLABRADA S.A.D.","visitante":"C.D. FUTBOL FEMENINO OLYMPIA LAS ROZAS \"B\"","equipoLocal_id":"4931602","equipoVisitante_id":"10932705","goles_local":0,"goles_visitante":0,"fecha":"2020-01-12","hora_prevista":"00:00:00","estado_partido":0,"observaciones":"","codigo_acta":0,"grupo_id":"11435979","estado":0},{"jornada":12,"local":"FEPE GETAFE III","visitante":"A.D. VILLAVICIOSA DE ODON","equipoLocal_id":"10652841","equipoVisitante_id":"10659189","goles_local":0,"goles_visitante":0,"fecha":"2020-01-12","hora_prevista":"00:00:00","estado_partido":0,"observaciones":"","codigo_acta":0,"grupo_id":"11435979","estado":0},{"jornada":12,"local":"E.F. CIUDAD DE GETAFE","visitante":"CLUB POLID. PARLA ESCUELA","equipoLocal_id":"10710455","equipoVisitante_id":"10658642","goles_local":0,"goles_visitante":0,"fecha":"2020-01-12","hora_prevista":"00:00:00","estado_partido":0,"observaciones":"","codigo_acta":0,"grupo_id":"11435979","estado":0},{"jornada":12,"local":"ESCUELA DE FUTBOL A.F.E. \"B\"","visitante":"S.A.D. FUNDACION RAYO VALLECANO \"B\"","equipoLocal_id":"6818319","equipoVisitante_id":"2729561","goles_local":0,"goles_visitante":0,"fecha":"2020-01-12","hora_prevista":"00:00:00","estado_partido":0,"observaciones":"","codigo_acta":0,"grupo_id":"11435979","estado":0},{"jornada":12,"local":"A.D. LA MECA DE RIVAS","visitante":"MADRID C.F. FEMENINO \"C\"","equipoLocal_id":"10659167","equipoVisitante_id":"10659400","goles_local":0,"goles_visitante":0,"fecha":"2020-01-12","hora_prevista":"00:00:00","estado_partido":0,"observaciones":"","codigo_acta":0,"grupo_id":"11435979","estado":0}],"13":[{"jornada":13,"local":"C.D. LIBERTAD ALCORCON","visitante":"C.D. RACING CALYPSO","equipoLocal_id":"8947854","equipoVisitante_id":"10946043","goles_local":0,"goles_visitante":0,"fecha":"2020-01-19","hora_prevista":"00:00:00","estado_partido":0,"observaciones":"","codigo_acta":0,"grupo_id":"11435979","estado":0},{"jornada":13,"local":"C.D. ESC.FUT. VILLA DE MADRID","visitante":"C.D.C. CIEMPOZUELOS","equipoLocal_id":"10761521","equipoVisitante_id":"6818240","goles_local":0,"goles_visitante":0,"fecha":"2020-01-19","hora_prevista":"00:00:00","estado_partido":0,"observaciones":"","codigo_acta":0,"grupo_id":"11435979","estado":0},{"jornada":13,"local":"A.D. FUTBOL SALA CHINCHON","visitante":"C.F. FUENLABRADA S.A.D.","equipoLocal_id":"4942038","equipoVisitante_id":"4931602","goles_local":0,"goles_visitante":0,"fecha":"2020-01-19","hora_prevista":"00:00:00","estado_partido":0,"observaciones":"","codigo_acta":0,"grupo_id":"11435979","estado":0},{"jornada":13,"local":"C.D. FUTBOL FEMENINO OLYMPIA LAS ROZAS \"B\"","visitante":"FEPE GETAFE III","equipoLocal_id":"10932705","equipoVisitante_id":"10652841","goles_local":0,"goles_visitante":0,"fecha":"2020-01-19","hora_prevista":"00:00:00","estado_partido":0,"observaciones":"","codigo_acta":0,"grupo_id":"11435979","estado":0},{"jornada":13,"local":"A.D. VILLAVICIOSA DE ODON","visitante":"E.F. CIUDAD DE GETAFE","equipoLocal_id":"10659189","equipoVisitante_id":"10710455","goles_local":0,"goles_visitante":0,"fecha":"2020-01-19","hora_prevista":"00:00:00","estado_partido":0,"observaciones":"","codigo_acta":0,"grupo_id":"11435979","estado":0},{"jornada":13,"local":"CLUB POLID. PARLA ESCUELA","visitante":"ESCUELA DE FUTBOL A.F.E. \"B\"","equipoLocal_id":"10658642","equipoVisitante_id":"6818319","goles_local":0,"goles_visitante":0,"fecha":"2020-01-19","hora_prevista":"00:00:00","estado_partido":0,"observaciones":"","codigo_acta":0,"grupo_id":"11435979","estado":0},{"jornada":13,"local":"S.A.D. FUNDACION RAYO VALLECANO \"B\"","visitante":"A.D. LA MECA DE RIVAS","equipoLocal_id":"2729561","equipoVisitante_id":"10659167","goles_local":0,"goles_visitante":0,"fecha":"2020-01-19","hora_prevista":"00:00:00","estado_partido":0,"observaciones":"","codigo_acta":0,"grupo_id":"11435979","estado":0},{"jornada":13,"local":"C.D. COLONIA MOSCARDO","visitante":"MADRID C.F. FEMENINO \"C\"","equipoLocal_id":"8929864","equipoVisitante_id":"10659400","goles_local":0,"goles_visitante":0,"fecha":"2020-01-19","hora_prevista":"00:00:00","estado_partido":0,"observaciones":"","codigo_acta":0,"grupo_id":"11435979","estado":0}],"14":[{"jornada":14,"local":"C.D. COLONIA MOSCARDO","visitante":"C.D. RACING CALYPSO","equipoLocal_id":"8929864","equipoVisitante_id":"10946043","goles_local":0,"goles_visitante":0,"fecha":"2020-01-26","hora_prevista":"00:00:00","estado_partido":0,"observaciones":"","codigo_acta":0,"grupo_id":"11435979","estado":0},{"jornada":14,"local":"C.D.C. CIEMPOZUELOS","visitante":"C.D. LIBERTAD ALCORCON","equipoLocal_id":"6818240","equipoVisitante_id":"8947854","goles_local":0,"goles_visitante":0,"fecha":"2020-01-26","hora_prevista":"00:00:00","estado_partido":0,"observaciones":"","codigo_acta":0,"grupo_id":"11435979","estado":0},{"jornada":14,"local":"C.F. FUENLABRADA S.A.D.","visitante":"C.D. ESC.FUT. VILLA DE MADRID","equipoLocal_id":"4931602","equipoVisitante_id":"10761521","goles_local":0,"goles_visitante":0,"fecha":"2020-01-26","hora_prevista":"00:00:00","estado_partido":0,"observaciones":"","codigo_acta":0,"grupo_id":"11435979","estado":0},{"jornada":14,"local":"FEPE GETAFE III","visitante":"A.D. FUTBOL SALA CHINCHON","equipoLocal_id":"10652841","equipoVisitante_id":"4942038","goles_local":0,"goles_visitante":0,"fecha":"2020-01-26","hora_prevista":"00:00:00","estado_partido":0,"observaciones":"","codigo_acta":0,"grupo_id":"11435979","estado":0},{"jornada":14,"local":"E.F. CIUDAD DE GETAFE","visitante":"C.D. FUTBOL FEMENINO OLYMPIA LAS ROZAS \"B\"","equipoLocal_id":"10710455","equipoVisitante_id":"10932705","goles_local":0,"goles_visitante":0,"fecha":"2020-01-26","hora_prevista":"00:00:00","estado_partido":0,"observaciones":"","codigo_acta":0,"grupo_id":"11435979","estado":0},{"jornada":14,"local":"ESCUELA DE FUTBOL A.F.E. \"B\"","visitante":"A.D. VILLAVICIOSA DE ODON","equipoLocal_id":"6818319","equipoVisitante_id":"10659189","goles_local":0,"goles_visitante":0,"fecha":"2020-01-26","hora_prevista":"00:00:00","estado_partido":0,"observaciones":"","codigo_acta":0,"grupo_id":"11435979","estado":0},{"jornada":14,"local":"A.D. LA MECA DE RIVAS","visitante":"CLUB POLID. PARLA ESCUELA","equipoLocal_id":"10659167","equipoVisitante_id":"10658642","goles_local":0,"goles_visitante":0,"fecha":"2020-01-26","hora_prevista":"00:00:00","estado_partido":0,"observaciones":"","codigo_acta":0,"grupo_id":"11435979","estado":0},{"jornada":14,"local":"MADRID C.F. FEMENINO \"C\"","visitante":"S.A.D. FUNDACION RAYO VALLECANO \"B\"","equipoLocal_id":"10659400","equipoVisitante_id":"2729561","goles_local":0,"goles_visitante":0,"fecha":"2020-01-26","hora_prevista":"00:00:00","estado_partido":0,"observaciones":"","codigo_acta":0,"grupo_id":"11435979","estado":0}],"15":[{"jornada":15,"local":"C.D. RACING CALYPSO","visitante":"C.D.C. CIEMPOZUELOS","equipoLocal_id":"10946043","equipoVisitante_id":"6818240","goles_local":0,"goles_visitante":0,"fecha":"2020-02-02","hora_prevista":"00:00:00","estado_partido":0,"observaciones":"","codigo_acta":0,"grupo_id":"11435979","estado":0},{"jornada":15,"local":"C.D. LIBERTAD ALCORCON","visitante":"C.F. FUENLABRADA S.A.D.","equipoLocal_id":"8947854","equipoVisitante_id":"4931602","goles_local":0,"goles_visitante":0,"fecha":"2020-02-02","hora_prevista":"00:00:00","estado_partido":0,"observaciones":"","codigo_acta":0,"grupo_id":"11435979","estado":0},{"jornada":15,"local":"C.D. ESC.FUT. VILLA DE MADRID","visitante":"FEPE GETAFE III","equipoLocal_id":"10761521","equipoVisitante_id":"10652841","goles_local":0,"goles_visitante":0,"fecha":"2020-02-02","hora_prevista":"00:00:00","estado_partido":0,"observaciones":"","codigo_acta":0,"grupo_id":"11435979","estado":0},{"jornada":15,"local":"A.D. FUTBOL SALA CHINCHON","visitante":"E.F. CIUDAD DE GETAFE","equipoLocal_id":"4942038","equipoVisitante_id":"10710455","goles_local":0,"goles_visitante":0,"fecha":"2020-02-02","hora_prevista":"00:00:00","estado_partido":0,"observaciones":"","codigo_acta":0,"grupo_id":"11435979","estado":0},{"jornada":15,"local":"C.D. FUTBOL FEMENINO OLYMPIA LAS ROZAS \"B\"","visitante":"ESCUELA DE FUTBOL A.F.E. \"B\"","equipoLocal_id":"10932705","equipoVisitante_id":"6818319","goles_local":0,"goles_visitante":0,"fecha":"2020-02-02","hora_prevista":"00:00:00","estado_partido":0,"observaciones":"","codigo_acta":0,"grupo_id":"11435979","estado":0},{"jornada":15,"local":"A.D. VILLAVICIOSA DE ODON","visitante":"A.D. LA MECA DE RIVAS","equipoLocal_id":"10659189","equipoVisitante_id":"10659167","goles_local":0,"goles_visitante":0,"fecha":"2020-02-02","hora_prevista":"00:00:00","estado_partido":0,"observaciones":"","codigo_acta":0,"grupo_id":"11435979","estado":0},{"jornada":15,"local":"CLUB POLID. PARLA ESCUELA","visitante":"MADRID C.F. FEMENINO \"C\"","equipoLocal_id":"10658642","equipoVisitante_id":"10659400","goles_local":0,"goles_visitante":0,"fecha":"2020-02-02","hora_prevista":"00:00:00","estado_partido":0,"observaciones":"","codigo_acta":0,"grupo_id":"11435979","estado":0},{"jornada":15,"local":"S.A.D. FUNDACION RAYO VALLECANO \"B\"","visitante":"C.D. COLONIA MOSCARDO","equipoLocal_id":"2729561","equipoVisitante_id":"8929864","goles_local":0,"goles_visitante":0,"fecha":"2020-02-02","hora_prevista":"00:00:00","estado_partido":0,"observaciones":"","codigo_acta":0,"grupo_id":"11435979","estado":0}],"16":[{"jornada":16,"local":"CLUB POLID. PARLA ESCUELA","visitante":"S.A.D. FUNDACION RAYO VALLECANO \"B\"","equipoLocal_id":"10658642","equipoVisitante_id":"2729561","goles_local":0,"goles_visitante":0,"fecha":"2020-02-09","hora_prevista":"00:00:00","estado_partido":0,"observaciones":"","codigo_acta":0,"grupo_id":"11435979","estado":0},{"jornada":16,"local":"A.D. VILLAVICIOSA DE ODON","visitante":"MADRID C.F. FEMENINO \"C\"","equipoLocal_id":"10659189","equipoVisitante_id":"10659400","goles_local":0,"goles_visitante":0,"fecha":"2020-02-09","hora_prevista":"00:00:00","estado_partido":0,"observaciones":"","codigo_acta":0,"grupo_id":"11435979","estado":0},{"jornada":16,"local":"C.D. FUTBOL FEMENINO OLYMPIA LAS ROZAS \"B\"","visitante":"A.D. LA MECA DE RIVAS","equipoLocal_id":"10932705","equipoVisitante_id":"10659167","goles_local":0,"goles_visitante":0,"fecha":"2020-02-09","hora_prevista":"00:00:00","estado_partido":0,"observaciones":"","codigo_acta":0,"grupo_id":"11435979","estado":0},{"jornada":16,"local":"A.D. FUTBOL SALA CHINCHON","visitante":"ESCUELA DE FUTBOL A.F.E. \"B\"","equipoLocal_id":"4942038","equipoVisitante_id":"6818319","goles_local":0,"goles_visitante":0,"fecha":"2020-02-09","hora_prevista":"00:00:00","estado_partido":0,"observaciones":"","codigo_acta":0,"grupo_id":"11435979","estado":0},{"jornada":16,"local":"C.D. ESC.FUT. VILLA DE MADRID","visitante":"E.F. CIUDAD DE GETAFE","equipoLocal_id":"10761521","equipoVisitante_id":"10710455","goles_local":0,"goles_visitante":0,"fecha":"2020-02-09","hora_prevista":"00:00:00","estado_partido":0,"observaciones":"","codigo_acta":0,"grupo_id":"11435979","estado":0},{"jornada":16,"local":"C.D. LIBERTAD ALCORCON","visitante":"FEPE GETAFE III","equipoLocal_id":"8947854","equipoVisitante_id":"10652841","goles_local":0,"goles_visitante":0,"fecha":"2020-02-09","hora_prevista":"00:00:00","estado_partido":0,"observaciones":"","codigo_acta":0,"grupo_id":"11435979","estado":0},{"jornada":16,"local":"C.D. RACING CALYPSO","visitante":"C.F. FUENLABRADA S.A.D.","equipoLocal_id":"10946043","equipoVisitante_id":"4931602","goles_local":0,"goles_visitante":0,"fecha":"2020-02-09","hora_prevista":"00:00:00","estado_partido":0,"observaciones":"","codigo_acta":0,"grupo_id":"11435979","estado":0},{"jornada":16,"local":"C.D.C. CIEMPOZUELOS","visitante":"C.D. COLONIA MOSCARDO","equipoLocal_id":"6818240","equipoVisitante_id":"8929864","goles_local":0,"goles_visitante":0,"fecha":"2020-02-09","hora_prevista":"00:00:00","estado_partido":0,"observaciones":"","codigo_acta":0,"grupo_id":"11435979","estado":0}],"17":[{"jornada":17,"local":"C.D. COLONIA MOSCARDO","visitante":"CLUB POLID. PARLA ESCUELA","equipoLocal_id":"8929864","equipoVisitante_id":"10658642","goles_local":0,"goles_visitante":0,"fecha":"2020-02-16","hora_prevista":"00:00:00","estado_partido":0,"observaciones":"","codigo_acta":0,"grupo_id":"11435979","estado":0},{"jornada":17,"local":"S.A.D. FUNDACION RAYO VALLECANO \"B\"","visitante":"A.D. VILLAVICIOSA DE ODON","equipoLocal_id":"2729561","equipoVisitante_id":"10659189","goles_local":0,"goles_visitante":0,"fecha":"2020-02-16","hora_prevista":"00:00:00","estado_partido":0,"observaciones":"","codigo_acta":0,"grupo_id":"11435979","estado":0},{"jornada":17,"local":"MADRID C.F. FEMENINO \"C\"","visitante":"C.D. FUTBOL FEMENINO OLYMPIA LAS ROZAS \"B\"","equipoLocal_id":"10659400","equipoVisitante_id":"10932705","goles_local":0,"goles_visitante":0,"fecha":"2020-02-16","hora_prevista":"00:00:00","estado_partido":0,"observaciones":"","codigo_acta":0,"grupo_id":"11435979","estado":0},{"jornada":17,"local":"A.D. LA MECA DE RIVAS","visitante":"A.D. FUTBOL SALA CHINCHON","equipoLocal_id":"10659167","equipoVisitante_id":"4942038","goles_local":0,"goles_visitante":0,"fecha":"2020-02-16","hora_prevista":"00:00:00","estado_partido":0,"observaciones":"","codigo_acta":0,"grupo_id":"11435979","estado":0},{"jornada":17,"local":"ESCUELA DE FUTBOL A.F.E. \"B\"","visitante":"C.D. ESC.FUT. VILLA DE MADRID","equipoLocal_id":"6818319","equipoVisitante_id":"10761521","goles_local":0,"goles_visitante":0,"fecha":"2020-02-16","hora_prevista":"00:00:00","estado_partido":0,"observaciones":"","codigo_acta":0,"grupo_id":"11435979","estado":0},{"jornada":17,"local":"E.F. CIUDAD DE GETAFE","visitante":"C.D. LIBERTAD ALCORCON","equipoLocal_id":"10710455","equipoVisitante_id":"8947854","goles_local":0,"goles_visitante":0,"fecha":"2020-02-16","hora_prevista":"00:00:00","estado_partido":0,"observaciones":"","codigo_acta":0,"grupo_id":"11435979","estado":0},{"jornada":17,"local":"FEPE GETAFE III","visitante":"C.D. RACING CALYPSO","equipoLocal_id":"10652841","equipoVisitante_id":"10946043","goles_local":0,"goles_visitante":0,"fecha":"2020-02-16","hora_prevista":"00:00:00","estado_partido":0,"observaciones":"","codigo_acta":0,"grupo_id":"11435979","estado":0},{"jornada":17,"local":"C.F. FUENLABRADA S.A.D.","visitante":"C.D.C. CIEMPOZUELOS","equipoLocal_id":"4931602","equipoVisitante_id":"6818240","goles_local":0,"goles_visitante":0,"fecha":"2020-02-16","hora_prevista":"00:00:00","estado_partido":0,"observaciones":"","codigo_acta":0,"grupo_id":"11435979","estado":0}],"18":[{"jornada":18,"local":"A.D. VILLAVICIOSA DE ODON","visitante":"CLUB POLID. PARLA ESCUELA","equipoLocal_id":"10659189","equipoVisitante_id":"10658642","goles_local":0,"goles_visitante":0,"fecha":"2020-02-23","hora_prevista":"00:00:00","estado_partido":0,"observaciones":"","codigo_acta":0,"grupo_id":"11435979","estado":0},{"jornada":18,"local":"C.D. FUTBOL FEMENINO OLYMPIA LAS ROZAS \"B\"","visitante":"S.A.D. FUNDACION RAYO VALLECANO \"B\"","equipoLocal_id":"10932705","equipoVisitante_id":"2729561","goles_local":0,"goles_visitante":0,"fecha":"2020-02-23","hora_prevista":"00:00:00","estado_partido":0,"observaciones":"","codigo_acta":0,"grupo_id":"11435979","estado":0},{"jornada":18,"local":"A.D. FUTBOL SALA CHINCHON","visitante":"MADRID C.F. FEMENINO \"C\"","equipoLocal_id":"4942038","equipoVisitante_id":"10659400","goles_local":0,"goles_visitante":0,"fecha":"2020-02-23","hora_prevista":"00:00:00","estado_partido":0,"observaciones":"","codigo_acta":0,"grupo_id":"11435979","estado":0},{"jornada":18,"local":"C.D. ESC.FUT. VILLA DE MADRID","visitante":"A.D. LA MECA DE RIVAS","equipoLocal_id":"10761521","equipoVisitante_id":"10659167","goles_local":0,"goles_visitante":0,"fecha":"2020-02-23","hora_prevista":"00:00:00","estado_partido":0,"observaciones":"","codigo_acta":0,"grupo_id":"11435979","estado":0},{"jornada":18,"local":"C.D. LIBERTAD ALCORCON","visitante":"ESCUELA DE FUTBOL A.F.E. \"B\"","equipoLocal_id":"8947854","equipoVisitante_id":"6818319","goles_local":0,"goles_visitante":0,"fecha":"2020-02-23","hora_prevista":"00:00:00","estado_partido":0,"observaciones":"","codigo_acta":0,"grupo_id":"11435979","estado":0},{"jornada":18,"local":"C.D. RACING CALYPSO","visitante":"E.F. CIUDAD DE GETAFE","equipoLocal_id":"10946043","equipoVisitante_id":"10710455","goles_local":0,"goles_visitante":0,"fecha":"2020-02-23","hora_prevista":"00:00:00","estado_partido":0,"observaciones":"","codigo_acta":0,"grupo_id":"11435979","estado":0},{"jornada":18,"local":"C.D.C. CIEMPOZUELOS","visitante":"FEPE GETAFE III","equipoLocal_id":"6818240","equipoVisitante_id":"10652841","goles_local":0,"goles_visitante":0,"fecha":"2020-02-23","hora_prevista":"00:00:00","estado_partido":0,"observaciones":"","codigo_acta":0,"grupo_id":"11435979","estado":0},{"jornada":18,"local":"C.F. FUENLABRADA S.A.D.","visitante":"C.D. COLONIA MOSCARDO","equipoLocal_id":"4931602","equipoVisitante_id":"8929864","goles_local":0,"goles_visitante":0,"fecha":"2020-02-23","hora_prevista":"00:00:00","estado_partido":0,"observaciones":"","codigo_acta":0,"grupo_id":"11435979","estado":0}],"19":[{"jornada":19,"local":"C.D. COLONIA MOSCARDO","visitante":"A.D. VILLAVICIOSA DE ODON","equipoLocal_id":"8929864","equipoVisitante_id":"10659189","goles_local":0,"goles_visitante":0,"fecha":"2020-03-01","hora_prevista":"00:00:00","estado_partido":0,"observaciones":"","codigo_acta":0,"grupo_id":"11435979","estado":0},{"jornada":19,"local":"CLUB POLID. PARLA ESCUELA","visitante":"C.D. FUTBOL FEMENINO OLYMPIA LAS ROZAS \"B\"","equipoLocal_id":"10658642","equipoVisitante_id":"10932705","goles_local":0,"goles_visitante":0,"fecha":"2020-03-01","hora_prevista":"00:00:00","estado_partido":0,"observaciones":"","codigo_acta":0,"grupo_id":"11435979","estado":0},{"jornada":19,"local":"S.A.D. FUNDACION RAYO VALLECANO \"B\"","visitante":"A.D. FUTBOL SALA CHINCHON","equipoLocal_id":"2729561","equipoVisitante_id":"4942038","goles_local":0,"goles_visitante":0,"fecha":"2020-03-01","hora_prevista":"00:00:00","estado_partido":0,"observaciones":"","codigo_acta":0,"grupo_id":"11435979","estado":0},{"jornada":19,"local":"MADRID C.F. FEMENINO \"C\"","visitante":"C.D. ESC.FUT. VILLA DE MADRID","equipoLocal_id":"10659400","equipoVisitante_id":"10761521","goles_local":0,"goles_visitante":0,"fecha":"2020-03-01","hora_prevista":"00:00:00","estado_partido":0,"observaciones":"","codigo_acta":0,"grupo_id":"11435979","estado":0},{"jornada":19,"local":"A.D. LA MECA DE RIVAS","visitante":"C.D. LIBERTAD ALCORCON","equipoLocal_id":"10659167","equipoVisitante_id":"8947854","goles_local":0,"goles_visitante":0,"fecha":"2020-03-01","hora_prevista":"00:00:00","estado_partido":0,"observaciones":"","codigo_acta":0,"grupo_id":"11435979","estado":0},{"jornada":19,"local":"ESCUELA DE FUTBOL A.F.E. \"B\"","visitante":"C.D. RACING CALYPSO","equipoLocal_id":"6818319","equipoVisitante_id":"10946043","goles_local":0,"goles_visitante":0,"fecha":"2020-03-01","hora_prevista":"00:00:00","estado_partido":0,"observaciones":"","codigo_acta":0,"grupo_id":"11435979","estado":0},{"jornada":19,"local":"E.F. CIUDAD DE GETAFE","visitante":"C.D.C. CIEMPOZUELOS","equipoLocal_id":"10710455","equipoVisitante_id":"6818240","goles_local":0,"goles_visitante":0,"fecha":"2020-03-01","hora_prevista":"00:00:00","estado_partido":0,"observaciones":"","codigo_acta":0,"grupo_id":"11435979","estado":0},{"jornada":19,"local":"FEPE GETAFE III","visitante":"C.F. FUENLABRADA S.A.D.","equipoLocal_id":"10652841","equipoVisitante_id":"4931602","goles_local":0,"goles_visitante":0,"fecha":"2020-03-01","hora_prevista":"00:00:00","estado_partido":0,"observaciones":"","codigo_acta":0,"grupo_id":"11435979","estado":0}],"20":[{"jornada":20,"local":"C.D. FUTBOL FEMENINO OLYMPIA LAS ROZAS \"B\"","visitante":"A.D. VILLAVICIOSA DE ODON","equipoLocal_id":"10932705","equipoVisitante_id":"10659189","goles_local":0,"goles_visitante":0,"fecha":"2020-03-08","hora_prevista":"00:00:00","estado_partido":0,"observaciones":"","codigo_acta":0,"grupo_id":"11435979","estado":0},{"jornada":20,"local":"A.D. FUTBOL SALA CHINCHON","visitante":"CLUB POLID. PARLA ESCUELA","equipoLocal_id":"4942038","equipoVisitante_id":"10658642","goles_local":0,"goles_visitante":0,"fecha":"2020-03-08","hora_prevista":"00:00:00","estado_partido":0,"observaciones":"","codigo_acta":0,"grupo_id":"11435979","estado":0},{"jornada":20,"local":"C.D. ESC.FUT. VILLA DE MADRID","visitante":"S.A.D. FUNDACION RAYO VALLECANO \"B\"","equipoLocal_id":"10761521","equipoVisitante_id":"2729561","goles_local":0,"goles_visitante":0,"fecha":"2020-03-08","hora_prevista":"00:00:00","estado_partido":0,"observaciones":"","codigo_acta":0,"grupo_id":"11435979","estado":0},{"jornada":20,"local":"C.D. LIBERTAD ALCORCON","visitante":"MADRID C.F. FEMENINO \"C\"","equipoLocal_id":"8947854","equipoVisitante_id":"10659400","goles_local":0,"goles_visitante":0,"fecha":"2020-03-08","hora_prevista":"00:00:00","estado_partido":0,"observaciones":"","codigo_acta":0,"grupo_id":"11435979","estado":0},{"jornada":20,"local":"C.D. RACING CALYPSO","visitante":"A.D. LA MECA DE RIVAS","equipoLocal_id":"10946043","equipoVisitante_id":"10659167","goles_local":0,"goles_visitante":0,"fecha":"2020-03-08","hora_prevista":"00:00:00","estado_partido":0,"observaciones":"","codigo_acta":0,"grupo_id":"11435979","estado":0},{"jornada":20,"local":"C.D.C. CIEMPOZUELOS","visitante":"ESCUELA DE FUTBOL A.F.E. \"B\"","equipoLocal_id":"6818240","equipoVisitante_id":"6818319","goles_local":0,"goles_visitante":0,"fecha":"2020-03-08","hora_prevista":"00:00:00","estado_partido":0,"observaciones":"","codigo_acta":0,"grupo_id":"11435979","estado":0},{"jornada":20,"local":"C.F. FUENLABRADA S.A.D.","visitante":"E.F. CIUDAD DE GETAFE","equipoLocal_id":"4931602","equipoVisitante_id":"10710455","goles_local":0,"goles_visitante":0,"fecha":"2020-03-08","hora_prevista":"00:00:00","estado_partido":0,"observaciones":"","codigo_acta":0,"grupo_id":"11435979","estado":0},{"jornada":20,"local":"FEPE GETAFE III","visitante":"C.D. COLONIA MOSCARDO","equipoLocal_id":"10652841","equipoVisitante_id":"8929864","goles_local":0,"goles_visitante":0,"fecha":"2020-03-08","hora_prevista":"00:00:00","estado_partido":0,"observaciones":"","codigo_acta":0,"grupo_id":"11435979","estado":0}],"21":[{"jornada":21,"local":"C.D. COLONIA MOSCARDO","visitante":"C.D. FUTBOL FEMENINO OLYMPIA LAS ROZAS \"B\"","equipoLocal_id":"8929864","equipoVisitante_id":"10932705","goles_local":0,"goles_visitante":0,"fecha":"2020-03-15","hora_prevista":"00:00:00","estado_partido":0,"observaciones":"","codigo_acta":0,"grupo_id":"11435979","estado":0},{"jornada":21,"local":"A.D. VILLAVICIOSA DE ODON","visitante":"A.D. FUTBOL SALA CHINCHON","equipoLocal_id":"10659189","equipoVisitante_id":"4942038","goles_local":0,"goles_visitante":0,"fecha":"2020-03-15","hora_prevista":"00:00:00","estado_partido":0,"observaciones":"","codigo_acta":0,"grupo_id":"11435979","estado":0},{"jornada":21,"local":"CLUB POLID. PARLA ESCUELA","visitante":"C.D. ESC.FUT. VILLA DE MADRID","equipoLocal_id":"10658642","equipoVisitante_id":"10761521","goles_local":0,"goles_visitante":0,"fecha":"2020-03-15","hora_prevista":"00:00:00","estado_partido":0,"observaciones":"","codigo_acta":0,"grupo_id":"11435979","estado":0},{"jornada":21,"local":"S.A.D. FUNDACION RAYO VALLECANO \"B\"","visitante":"C.D. LIBERTAD ALCORCON","equipoLocal_id":"2729561","equipoVisitante_id":"8947854","goles_local":0,"goles_visitante":0,"fecha":"2020-03-15","hora_prevista":"00:00:00","estado_partido":0,"observaciones":"","codigo_acta":0,"grupo_id":"11435979","estado":0},{"jornada":21,"local":"MADRID C.F. FEMENINO \"C\"","visitante":"C.D. RACING CALYPSO","equipoLocal_id":"10659400","equipoVisitante_id":"10946043","goles_local":0,"goles_visitante":0,"fecha":"2020-03-15","hora_prevista":"00:00:00","estado_partido":0,"observaciones":"","codigo_acta":0,"grupo_id":"11435979","estado":0},{"jornada":21,"local":"A.D. LA MECA DE RIVAS","visitante":"C.D.C. CIEMPOZUELOS","equipoLocal_id":"10659167","equipoVisitante_id":"6818240","goles_local":0,"goles_visitante":0,"fecha":"2020-03-15","hora_prevista":"00:00:00","estado_partido":0,"observaciones":"","codigo_acta":0,"grupo_id":"11435979","estado":0},{"jornada":21,"local":"ESCUELA DE FUTBOL A.F.E. \"B\"","visitante":"C.F. FUENLABRADA S.A.D.","equipoLocal_id":"6818319","equipoVisitante_id":"4931602","goles_local":0,"goles_visitante":0,"fecha":"2020-03-15","hora_prevista":"00:00:00","estado_partido":0,"observaciones":"","codigo_acta":0,"grupo_id":"11435979","estado":0},{"jornada":21,"local":"E.F. CIUDAD DE GETAFE","visitante":"FEPE GETAFE III","equipoLocal_id":"10710455","equipoVisitante_id":"10652841","goles_local":0,"goles_visitante":0,"fecha":"2020-03-15","hora_prevista":"00:00:00","estado_partido":0,"observaciones":"","codigo_acta":0,"grupo_id":"11435979","estado":0}],"22":[{"jornada":22,"local":"A.D. FUTBOL SALA CHINCHON","visitante":"C.D. FUTBOL FEMENINO OLYMPIA LAS ROZAS \"B\"","equipoLocal_id":"4942038","equipoVisitante_id":"10932705","goles_local":0,"goles_visitante":0,"fecha":"2020-03-22","hora_prevista":"00:00:00","estado_partido":0,"observaciones":"","codigo_acta":0,"grupo_id":"11435979","estado":0},{"jornada":22,"local":"C.D. ESC.FUT. VILLA DE MADRID","visitante":"A.D. VILLAVICIOSA DE ODON","equipoLocal_id":"10761521","equipoVisitante_id":"10659189","goles_local":0,"goles_visitante":0,"fecha":"2020-03-22","hora_prevista":"00:00:00","estado_partido":0,"observaciones":"","codigo_acta":0,"grupo_id":"11435979","estado":0},{"jornada":22,"local":"C.D. LIBERTAD ALCORCON","visitante":"CLUB POLID. PARLA ESCUELA","equipoLocal_id":"8947854","equipoVisitante_id":"10658642","goles_local":0,"goles_visitante":0,"fecha":"2020-03-22","hora_prevista":"00:00:00","estado_partido":0,"observaciones":"","codigo_acta":0,"grupo_id":"11435979","estado":0},{"jornada":22,"local":"C.D. RACING CALYPSO","visitante":"S.A.D. FUNDACION RAYO VALLECANO \"B\"","equipoLocal_id":"10946043","equipoVisitante_id":"2729561","goles_local":0,"goles_visitante":0,"fecha":"2020-03-22","hora_prevista":"00:00:00","estado_partido":0,"observaciones":"","codigo_acta":0,"grupo_id":"11435979","estado":0},{"jornada":22,"local":"C.D.C. CIEMPOZUELOS","visitante":"MADRID C.F. FEMENINO \"C\"","equipoLocal_id":"6818240","equipoVisitante_id":"10659400","goles_local":0,"goles_visitante":0,"fecha":"2020-03-22","hora_prevista":"00:00:00","estado_partido":0,"observaciones":"","codigo_acta":0,"grupo_id":"11435979","estado":0},{"jornada":22,"local":"C.F. FUENLABRADA S.A.D.","visitante":"A.D. LA MECA DE RIVAS","equipoLocal_id":"4931602","equipoVisitante_id":"10659167","goles_local":0,"goles_visitante":0,"fecha":"2020-03-22","hora_prevista":"00:00:00","estado_partido":0,"observaciones":"","codigo_acta":0,"grupo_id":"11435979","estado":0},{"jornada":22,"local":"FEPE GETAFE III","visitante":"ESCUELA DE FUTBOL A.F.E. \"B\"","equipoLocal_id":"10652841","equipoVisitante_id":"6818319","goles_local":0,"goles_visitante":0,"fecha":"2020-03-22","hora_prevista":"00:00:00","estado_partido":0,"observaciones":"","codigo_acta":0,"grupo_id":"11435979","estado":0},{"jornada":22,"local":"E.F. CIUDAD DE GETAFE","visitante":"C.D. COLONIA MOSCARDO","equipoLocal_id":"10710455","equipoVisitante_id":"8929864","goles_local":0,"goles_visitante":0,"fecha":"2020-03-22","hora_prevista":"00:00:00","estado_partido":0,"observaciones":"","codigo_acta":0,"grupo_id":"11435979","estado":0}],"23":[{"jornada":23,"local":"C.D. COLONIA MOSCARDO","visitante":"A.D. FUTBOL SALA CHINCHON","equipoLocal_id":"8929864","equipoVisitante_id":"4942038","goles_local":0,"goles_visitante":0,"fecha":"2020-03-29","hora_prevista":"00:00:00","estado_partido":0,"observaciones":"","codigo_acta":0,"grupo_id":"11435979","estado":0},{"jornada":23,"local":"C.D. FUTBOL FEMENINO OLYMPIA LAS ROZAS \"B\"","visitante":"C.D. ESC.FUT. VILLA DE MADRID","equipoLocal_id":"10932705","equipoVisitante_id":"10761521","goles_local":0,"goles_visitante":0,"fecha":"2020-03-29","hora_prevista":"00:00:00","estado_partido":0,"observaciones":"","codigo_acta":0,"grupo_id":"11435979","estado":0},{"jornada":23,"local":"A.D. VILLAVICIOSA DE ODON","visitante":"C.D. LIBERTAD ALCORCON","equipoLocal_id":"10659189","equipoVisitante_id":"8947854","goles_local":0,"goles_visitante":0,"fecha":"2020-03-29","hora_prevista":"00:00:00","estado_partido":0,"observaciones":"","codigo_acta":0,"grupo_id":"11435979","estado":0},{"jornada":23,"local":"CLUB POLID. PARLA ESCUELA","visitante":"C.D. RACING CALYPSO","equipoLocal_id":"10658642","equipoVisitante_id":"10946043","goles_local":0,"goles_visitante":0,"fecha":"2020-03-29","hora_prevista":"00:00:00","estado_partido":0,"observaciones":"","codigo_acta":0,"grupo_id":"11435979","estado":0},{"jornada":23,"local":"S.A.D. FUNDACION RAYO VALLECANO \"B\"","visitante":"C.D.C. CIEMPOZUELOS","equipoLocal_id":"2729561","equipoVisitante_id":"6818240","goles_local":0,"goles_visitante":0,"fecha":"2020-03-29","hora_prevista":"00:00:00","estado_partido":0,"observaciones":"","codigo_acta":0,"grupo_id":"11435979","estado":0},{"jornada":23,"local":"MADRID C.F. FEMENINO \"C\"","visitante":"C.F. FUENLABRADA S.A.D.","equipoLocal_id":"10659400","equipoVisitante_id":"4931602","goles_local":0,"goles_visitante":0,"fecha":"2020-03-29","hora_prevista":"00:00:00","estado_partido":0,"observaciones":"","codigo_acta":0,"grupo_id":"11435979","estado":0},{"jornada":23,"local":"A.D. LA MECA DE RIVAS","visitante":"FEPE GETAFE III","equipoLocal_id":"10659167","equipoVisitante_id":"10652841","goles_local":0,"goles_visitante":0,"fecha":"2020-03-29","hora_prevista":"00:00:00","estado_partido":0,"observaciones":"","codigo_acta":0,"grupo_id":"11435979","estado":0},{"jornada":23,"local":"ESCUELA DE FUTBOL A.F.E. \"B\"","visitante":"E.F. CIUDAD DE GETAFE","equipoLocal_id":"6818319","equipoVisitante_id":"10710455","goles_local":0,"goles_visitante":0,"fecha":"2020-03-29","hora_prevista":"00:00:00","estado_partido":0,"observaciones":"","codigo_acta":0,"grupo_id":"11435979","estado":0}],"24":[{"jornada":24,"local":"C.D. ESC.FUT. VILLA DE MADRID","visitante":"A.D. FUTBOL SALA CHINCHON","equipoLocal_id":"10761521","equipoVisitante_id":"4942038","goles_local":0,"goles_visitante":0,"fecha":"2020-04-19","hora_prevista":"00:00:00","estado_partido":0,"observaciones":"","codigo_acta":0,"grupo_id":"11435979","estado":0},{"jornada":24,"local":"C.D. LIBERTAD ALCORCON","visitante":"C.D. FUTBOL FEMENINO OLYMPIA LAS ROZAS \"B\"","equipoLocal_id":"8947854","equipoVisitante_id":"10932705","goles_local":0,"goles_visitante":0,"fecha":"2020-04-19","hora_prevista":"00:00:00","estado_partido":0,"observaciones":"","codigo_acta":0,"grupo_id":"11435979","estado":0},{"jornada":24,"local":"C.D. RACING CALYPSO","visitante":"A.D. VILLAVICIOSA DE ODON","equipoLocal_id":"10946043","equipoVisitante_id":"10659189","goles_local":0,"goles_visitante":0,"fecha":"2020-04-19","hora_prevista":"00:00:00","estado_partido":0,"observaciones":"","codigo_acta":0,"grupo_id":"11435979","estado":0},{"jornada":24,"local":"C.D.C. CIEMPOZUELOS","visitante":"CLUB POLID. PARLA ESCUELA","equipoLocal_id":"6818240","equipoVisitante_id":"10658642","goles_local":0,"goles_visitante":0,"fecha":"2020-04-19","hora_prevista":"00:00:00","estado_partido":0,"observaciones":"","codigo_acta":0,"grupo_id":"11435979","estado":0},{"jornada":24,"local":"C.F. FUENLABRADA S.A.D.","visitante":"S.A.D. FUNDACION RAYO VALLECANO \"B\"","equipoLocal_id":"4931602","equipoVisitante_id":"2729561","goles_local":0,"goles_visitante":0,"fecha":"2020-04-19","hora_prevista":"00:00:00","estado_partido":0,"observaciones":"","codigo_acta":0,"grupo_id":"11435979","estado":0},{"jornada":24,"local":"FEPE GETAFE III","visitante":"MADRID C.F. FEMENINO \"C\"","equipoLocal_id":"10652841","equipoVisitante_id":"10659400","goles_local":0,"goles_visitante":0,"fecha":"2020-04-19","hora_prevista":"00:00:00","estado_partido":0,"observaciones":"","codigo_acta":0,"grupo_id":"11435979","estado":0},{"jornada":24,"local":"E.F. CIUDAD DE GETAFE","visitante":"A.D. LA MECA DE RIVAS","equipoLocal_id":"10710455","equipoVisitante_id":"10659167","goles_local":0,"goles_visitante":0,"fecha":"2020-04-19","hora_prevista":"00:00:00","estado_partido":0,"observaciones":"","codigo_acta":0,"grupo_id":"11435979","estado":0},{"jornada":24,"local":"ESCUELA DE FUTBOL A.F.E. \"B\"","visitante":"C.D. COLONIA MOSCARDO","equipoLocal_id":"6818319","equipoVisitante_id":"8929864","goles_local":0,"goles_visitante":0,"fecha":"2020-04-19","hora_prevista":"00:00:00","estado_partido":0,"observaciones":"","codigo_acta":0,"grupo_id":"11435979","estado":0}],"25":[{"jornada":25,"local":"C.D. COLONIA MOSCARDO","visitante":"C.D. ESC.FUT. VILLA DE MADRID","equipoLocal_id":"8929864","equipoVisitante_id":"10761521","goles_local":0,"goles_visitante":0,"fecha":"2020-04-26","hora_prevista":"00:00:00","estado_partido":0,"observaciones":"","codigo_acta":0,"grupo_id":"11435979","estado":0},{"jornada":25,"local":"A.D. FUTBOL SALA CHINCHON","visitante":"C.D. LIBERTAD ALCORCON","equipoLocal_id":"4942038","equipoVisitante_id":"8947854","goles_local":0,"goles_visitante":0,"fecha":"2020-04-26","hora_prevista":"00:00:00","estado_partido":0,"observaciones":"","codigo_acta":0,"grupo_id":"11435979","estado":0},{"jornada":25,"local":"C.D. FUTBOL FEMENINO OLYMPIA LAS ROZAS \"B\"","visitante":"C.D. RACING CALYPSO","equipoLocal_id":"10932705","equipoVisitante_id":"10946043","goles_local":0,"goles_visitante":0,"fecha":"2020-04-26","hora_prevista":"00:00:00","estado_partido":0,"observaciones":"","codigo_acta":0,"grupo_id":"11435979","estado":0},{"jornada":25,"local":"A.D. VILLAVICIOSA DE ODON","visitante":"C.D.C. CIEMPOZUELOS","equipoLocal_id":"10659189","equipoVisitante_id":"6818240","goles_local":0,"goles_visitante":0,"fecha":"2020-04-26","hora_prevista":"00:00:00","estado_partido":0,"observaciones":"","codigo_acta":0,"grupo_id":"11435979","estado":0},{"jornada":25,"local":"CLUB POLID. PARLA ESCUELA","visitante":"C.F. FUENLABRADA S.A.D.","equipoLocal_id":"10658642","equipoVisitante_id":"4931602","goles_local":0,"goles_visitante":0,"fecha":"2020-04-26","hora_prevista":"00:00:00","estado_partido":0,"observaciones":"","codigo_acta":0,"grupo_id":"11435979","estado":0},{"jornada":25,"local":"S.A.D. FUNDACION RAYO VALLECANO \"B\"","visitante":"FEPE GETAFE III","equipoLocal_id":"2729561","equipoVisitante_id":"10652841","goles_local":0,"goles_visitante":0,"fecha":"2020-04-26","hora_prevista":"00:00:00","estado_partido":0,"observaciones":"","codigo_acta":0,"grupo_id":"11435979","estado":0},{"jornada":25,"local":"MADRID C.F. FEMENINO \"C\"","visitante":"E.F. CIUDAD DE GETAFE","equipoLocal_id":"10659400","equipoVisitante_id":"10710455","goles_local":0,"goles_visitante":0,"fecha":"2020-04-26","hora_prevista":"00:00:00","estado_partido":0,"observaciones":"","codigo_acta":0,"grupo_id":"11435979","estado":0},{"jornada":25,"local":"A.D. LA MECA DE RIVAS","visitante":"ESCUELA DE FUTBOL A.F.E. \"B\"","equipoLocal_id":"10659167","equipoVisitante_id":"6818319","goles_local":0,"goles_visitante":0,"fecha":"2020-04-26","hora_prevista":"00:00:00","estado_partido":0,"observaciones":"","codigo_acta":0,"grupo_id":"11435979","estado":0}],"26":[{"jornada":26,"local":"C.D. LIBERTAD ALCORCON","visitante":"C.D. ESC.FUT. VILLA DE MADRID","equipoLocal_id":"8947854","equipoVisitante_id":"10761521","goles_local":0,"goles_visitante":0,"fecha":"2020-05-10","hora_prevista":"00:00:00","estado_partido":0,"observaciones":"","codigo_acta":0,"grupo_id":"11435979","estado":0},{"jornada":26,"local":"C.D. RACING CALYPSO","visitante":"A.D. FUTBOL SALA CHINCHON","equipoLocal_id":"10946043","equipoVisitante_id":"4942038","goles_local":0,"goles_visitante":0,"fecha":"2020-05-10","hora_prevista":"00:00:00","estado_partido":0,"observaciones":"","codigo_acta":0,"grupo_id":"11435979","estado":0},{"jornada":26,"local":"C.D.C. CIEMPOZUELOS","visitante":"C.D. FUTBOL FEMENINO OLYMPIA LAS ROZAS \"B\"","equipoLocal_id":"6818240","equipoVisitante_id":"10932705","goles_local":0,"goles_visitante":0,"fecha":"2020-05-10","hora_prevista":"00:00:00","estado_partido":0,"observaciones":"","codigo_acta":0,"grupo_id":"11435979","estado":0},{"jornada":26,"local":"C.F. FUENLABRADA S.A.D.","visitante":"A.D. VILLAVICIOSA DE ODON","equipoLocal_id":"4931602","equipoVisitante_id":"10659189","goles_local":0,"goles_visitante":0,"fecha":"2020-05-10","hora_prevista":"00:00:00","estado_partido":0,"observaciones":"","codigo_acta":0,"grupo_id":"11435979","estado":0},{"jornada":26,"local":"FEPE GETAFE III","visitante":"CLUB POLID. PARLA ESCUELA","equipoLocal_id":"10652841","equipoVisitante_id":"10658642","goles_local":0,"goles_visitante":0,"fecha":"2020-05-10","hora_prevista":"00:00:00","estado_partido":0,"observaciones":"","codigo_acta":0,"grupo_id":"11435979","estado":0},{"jornada":26,"local":"E.F. CIUDAD DE GETAFE","visitante":"S.A.D. FUNDACION RAYO VALLECANO \"B\"","equipoLocal_id":"10710455","equipoVisitante_id":"2729561","goles_local":0,"goles_visitante":0,"fecha":"2020-05-10","hora_prevista":"00:00:00","estado_partido":0,"observaciones":"","codigo_acta":0,"grupo_id":"11435979","estado":0},{"jornada":26,"local":"ESCUELA DE FUTBOL A.F.E. \"B\"","visitante":"MADRID C.F. FEMENINO \"C\"","equipoLocal_id":"6818319","equipoVisitante_id":"10659400","goles_local":0,"goles_visitante":0,"fecha":"2020-05-10","hora_prevista":"00:00:00","estado_partido":0,"observaciones":"","codigo_acta":0,"grupo_id":"11435979","estado":0},{"jornada":26,"local":"A.D. LA MECA DE RIVAS","visitante":"C.D. COLONIA MOSCARDO","equipoLocal_id":"10659167","equipoVisitante_id":"8929864","goles_local":0,"goles_visitante":0,"fecha":"2020-05-10","hora_prevista":"00:00:00","estado_partido":0,"observaciones":"","codigo_acta":0,"grupo_id":"11435979","estado":0}],"27":[{"jornada":27,"local":"C.D. COLONIA MOSCARDO","visitante":"C.D. LIBERTAD ALCORCON","equipoLocal_id":"8929864","equipoVisitante_id":"8947854","goles_local":0,"goles_visitante":0,"fecha":"2020-05-17","hora_prevista":"00:00:00","estado_partido":0,"observaciones":"","codigo_acta":0,"grupo_id":"11435979","estado":0},{"jornada":27,"local":"C.D. ESC.FUT. VILLA DE MADRID","visitante":"C.D. RACING CALYPSO","equipoLocal_id":"10761521","equipoVisitante_id":"10946043","goles_local":0,"goles_visitante":0,"fecha":"2020-05-17","hora_prevista":"00:00:00","estado_partido":0,"observaciones":"","codigo_acta":0,"grupo_id":"11435979","estado":0},{"jornada":27,"local":"A.D. FUTBOL SALA CHINCHON","visitante":"C.D.C. CIEMPOZUELOS","equipoLocal_id":"4942038","equipoVisitante_id":"6818240","goles_local":0,"goles_visitante":0,"fecha":"2020-05-17","hora_prevista":"00:00:00","estado_partido":0,"observaciones":"","codigo_acta":0,"grupo_id":"11435979","estado":0},{"jornada":27,"local":"C.D. FUTBOL FEMENINO OLYMPIA LAS ROZAS \"B\"","visitante":"C.F. FUENLABRADA S.A.D.","equipoLocal_id":"10932705","equipoVisitante_id":"4931602","goles_local":0,"goles_visitante":0,"fecha":"2020-05-17","hora_prevista":"00:00:00","estado_partido":0,"observaciones":"","codigo_acta":0,"grupo_id":"11435979","estado":0},{"jornada":27,"local":"A.D. VILLAVICIOSA DE ODON","visitante":"FEPE GETAFE III","equipoLocal_id":"10659189","equipoVisitante_id":"10652841","goles_local":0,"goles_visitante":0,"fecha":"2020-05-17","hora_prevista":"00:00:00","estado_partido":0,"observaciones":"","codigo_acta":0,"grupo_id":"11435979","estado":0},{"jornada":27,"local":"CLUB POLID. PARLA ESCUELA","visitante":"E.F. CIUDAD DE GETAFE","equipoLocal_id":"10658642","equipoVisitante_id":"10710455","goles_local":0,"goles_visitante":0,"fecha":"2020-05-17","hora_prevista":"00:00:00","estado_partido":0,"observaciones":"","codigo_acta":0,"grupo_id":"11435979","estado":0},{"jornada":27,"local":"S.A.D. FUNDACION RAYO VALLECANO \"B\"","visitante":"ESCUELA DE FUTBOL A.F.E. \"B\"","equipoLocal_id":"2729561","equipoVisitante_id":"6818319","goles_local":0,"goles_visitante":0,"fecha":"2020-05-17","hora_prevista":"00:00:00","estado_partido":0,"observaciones":"","codigo_acta":0,"grupo_id":"11435979","estado":0},{"jornada":27,"local":"MADRID C.F. FEMENINO \"C\"","visitante":"A.D. LA MECA DE RIVAS","equipoLocal_id":"10659400","equipoVisitante_id":"10659167","goles_local":0,"goles_visitante":0,"fecha":"2020-05-17","hora_prevista":"00:00:00","estado_partido":0,"observaciones":"","codigo_acta":0,"grupo_id":"11435979","estado":0}],"28":[{"jornada":28,"local":"C.D. RACING CALYPSO","visitante":"C.D. LIBERTAD ALCORCON","equipoLocal_id":"10946043","equipoVisitante_id":"8947854","goles_local":0,"goles_visitante":0,"fecha":"2020-05-24","hora_prevista":"00:00:00","estado_partido":0,"observaciones":"","codigo_acta":0,"grupo_id":"11435979","estado":0},{"jornada":28,"local":"C.D.C. CIEMPOZUELOS","visitante":"C.D. ESC.FUT. VILLA DE MADRID","equipoLocal_id":"6818240","equipoVisitante_id":"10761521","goles_local":0,"goles_visitante":0,"fecha":"2020-05-24","hora_prevista":"00:00:00","estado_partido":0,"observaciones":"","codigo_acta":0,"grupo_id":"11435979","estado":0},{"jornada":28,"local":"C.F. FUENLABRADA S.A.D.","visitante":"A.D. FUTBOL SALA CHINCHON","equipoLocal_id":"4931602","equipoVisitante_id":"4942038","goles_local":0,"goles_visitante":0,"fecha":"2020-05-24","hora_prevista":"00:00:00","estado_partido":0,"observaciones":"","codigo_acta":0,"grupo_id":"11435979","estado":0},{"jornada":28,"local":"FEPE GETAFE III","visitante":"C.D. FUTBOL FEMENINO OLYMPIA LAS ROZAS \"B\"","equipoLocal_id":"10652841","equipoVisitante_id":"10932705","goles_local":0,"goles_visitante":0,"fecha":"2020-05-24","hora_prevista":"00:00:00","estado_partido":0,"observaciones":"","codigo_acta":0,"grupo_id":"11435979","estado":0},{"jornada":28,"local":"E.F. CIUDAD DE GETAFE","visitante":"A.D. VILLAVICIOSA DE ODON","equipoLocal_id":"10710455","equipoVisitante_id":"10659189","goles_local":0,"goles_visitante":0,"fecha":"2020-05-24","hora_prevista":"00:00:00","estado_partido":0,"observaciones":"","codigo_acta":0,"grupo_id":"11435979","estado":0},{"jornada":28,"local":"ESCUELA DE FUTBOL A.F.E. \"B\"","visitante":"CLUB POLID. PARLA ESCUELA","equipoLocal_id":"6818319","equipoVisitante_id":"10658642","goles_local":0,"goles_visitante":0,"fecha":"2020-05-24","hora_prevista":"00:00:00","estado_partido":0,"observaciones":"","codigo_acta":0,"grupo_id":"11435979","estado":0},{"jornada":28,"local":"A.D. LA MECA DE RIVAS","visitante":"S.A.D. FUNDACION RAYO VALLECANO \"B\"","equipoLocal_id":"10659167","equipoVisitante_id":"2729561","goles_local":0,"goles_visitante":0,"fecha":"2020-05-24","hora_prevista":"00:00:00","estado_partido":0,"observaciones":"","codigo_acta":0,"grupo_id":"11435979","estado":0},{"jornada":28,"local":"MADRID C.F. FEMENINO \"C\"","visitante":"C.D. COLONIA MOSCARDO","equipoLocal_id":"10659400","equipoVisitante_id":"8929864","goles_local":0,"goles_visitante":0,"fecha":"2020-05-24","hora_prevista":"00:00:00","estado_partido":0,"observaciones":"","codigo_acta":0,"grupo_id":"11435979","estado":0}],"29":[{"jornada":29,"local":"C.D. RACING CALYPSO","visitante":"C.D. COLONIA MOSCARDO","equipoLocal_id":"10946043","equipoVisitante_id":"8929864","goles_local":0,"goles_visitante":0,"fecha":"2020-05-31","hora_prevista":"00:00:00","estado_partido":0,"observaciones":"","codigo_acta":0,"grupo_id":"11435979","estado":0},{"jornada":29,"local":"C.D. LIBERTAD ALCORCON","visitante":"C.D.C. CIEMPOZUELOS","equipoLocal_id":"8947854","equipoVisitante_id":"6818240","goles_local":0,"goles_visitante":0,"fecha":"2020-05-31","hora_prevista":"00:00:00","estado_partido":0,"observaciones":"","codigo_acta":0,"grupo_id":"11435979","estado":0},{"jornada":29,"local":"C.D. ESC.FUT. VILLA DE MADRID","visitante":"C.F. FUENLABRADA S.A.D.","equipoLocal_id":"10761521","equipoVisitante_id":"4931602","goles_local":0,"goles_visitante":0,"fecha":"2020-05-31","hora_prevista":"00:00:00","estado_partido":0,"observaciones":"","codigo_acta":0,"grupo_id":"11435979","estado":0},{"jornada":29,"local":"A.D. FUTBOL SALA CHINCHON","visitante":"FEPE GETAFE III","equipoLocal_id":"4942038","equipoVisitante_id":"10652841","goles_local":0,"goles_visitante":0,"fecha":"2020-05-31","hora_prevista":"00:00:00","estado_partido":0,"observaciones":"","codigo_acta":0,"grupo_id":"11435979","estado":0},{"jornada":29,"local":"C.D. FUTBOL FEMENINO OLYMPIA LAS ROZAS \"B\"","visitante":"E.F. CIUDAD DE GETAFE","equipoLocal_id":"10932705","equipoVisitante_id":"10710455","goles_local":0,"goles_visitante":0,"fecha":"2020-05-31","hora_prevista":"00:00:00","estado_partido":0,"observaciones":"","codigo_acta":0,"grupo_id":"11435979","estado":0},{"jornada":29,"local":"A.D. VILLAVICIOSA DE ODON","visitante":"ESCUELA DE FUTBOL A.F.E. \"B\"","equipoLocal_id":"10659189","equipoVisitante_id":"6818319","goles_local":0,"goles_visitante":0,"fecha":"2020-05-31","hora_prevista":"00:00:00","estado_partido":0,"observaciones":"","codigo_acta":0,"grupo_id":"11435979","estado":0},{"jornada":29,"local":"CLUB POLID. PARLA ESCUELA","visitante":"A.D. LA MECA DE RIVAS","equipoLocal_id":"10658642","equipoVisitante_id":"10659167","goles_local":0,"goles_visitante":0,"fecha":"2020-05-31","hora_prevista":"00:00:00","estado_partido":0,"observaciones":"","codigo_acta":0,"grupo_id":"11435979","estado":0},{"jornada":29,"local":"S.A.D. FUNDACION RAYO VALLECANO \"B\"","visitante":"MADRID C.F. FEMENINO \"C\"","equipoLocal_id":"2729561","equipoVisitante_id":"10659400","goles_local":0,"goles_visitante":0,"fecha":"2020-05-31","hora_prevista":"00:00:00","estado_partido":0,"observaciones":"","codigo_acta":0,"grupo_id":"11435979","estado":0}],"30":[{"jornada":30,"local":"C.D.C. CIEMPOZUELOS","visitante":"C.D. RACING CALYPSO","equipoLocal_id":"6818240","equipoVisitante_id":"10946043","goles_local":0,"goles_visitante":0,"fecha":"2020-06-07","hora_prevista":"00:00:00","estado_partido":0,"observaciones":"","codigo_acta":0,"grupo_id":"11435979","estado":0},{"jornada":30,"local":"C.F. FUENLABRADA S.A.D.","visitante":"C.D. LIBERTAD ALCORCON","equipoLocal_id":"4931602","equipoVisitante_id":"8947854","goles_local":0,"goles_visitante":0,"fecha":"2020-06-07","hora_prevista":"00:00:00","estado_partido":0,"observaciones":"","codigo_acta":0,"grupo_id":"11435979","estado":0},{"jornada":30,"local":"FEPE GETAFE III","visitante":"C.D. ESC.FUT. VILLA DE MADRID","equipoLocal_id":"10652841","equipoVisitante_id":"10761521","goles_local":0,"goles_visitante":0,"fecha":"2020-06-07","hora_prevista":"00:00:00","estado_partido":0,"observaciones":"","codigo_acta":0,"grupo_id":"11435979","estado":0},{"jornada":30,"local":"E.F. CIUDAD DE GETAFE","visitante":"A.D. FUTBOL SALA CHINCHON","equipoLocal_id":"10710455","equipoVisitante_id":"4942038","goles_local":0,"goles_visitante":0,"fecha":"2020-06-07","hora_prevista":"00:00:00","estado_partido":0,"observaciones":"","codigo_acta":0,"grupo_id":"11435979","estado":0},{"jornada":30,"local":"ESCUELA DE FUTBOL A.F.E. \"B\"","visitante":"C.D. FUTBOL FEMENINO OLYMPIA LAS ROZAS \"B\"","equipoLocal_id":"6818319","equipoVisitante_id":"10932705","goles_local":0,"goles_visitante":0,"fecha":"2020-06-07","hora_prevista":"00:00:00","estado_partido":0,"observaciones":"","codigo_acta":0,"grupo_id":"11435979","estado":0},{"jornada":30,"local":"A.D. LA MECA DE RIVAS","visitante":"A.D. VILLAVICIOSA DE ODON","equipoLocal_id":"10659167","equipoVisitante_id":"10659189","goles_local":0,"goles_visitante":0,"fecha":"2020-06-07","hora_prevista":"00:00:00","estado_partido":0,"observaciones":"","codigo_acta":0,"grupo_id":"11435979","estado":0},{"jornada":30,"local":"MADRID C.F. FEMENINO \"C\"","visitante":"CLUB POLID. PARLA ESCUELA","equipoLocal_id":"10659400","equipoVisitante_id":"10658642","goles_local":0,"goles_visitante":0,"fecha":"2020-06-07","hora_prevista":"00:00:00","estado_partido":0,"observaciones":"","codigo_acta":0,"grupo_id":"11435979","estado":0},{"jornada":30,"local":"C.D. COLONIA MOSCARDO","visitante":"S.A.D. FUNDACION RAYO VALLECANO \"B\"","equipoLocal_id":"8929864","equipoVisitante_id":"2729561","goles_local":0,"goles_visitante":0,"fecha":"2020-06-07","hora_prevista":"00:00:00","estado_partido":0,"observaciones":"","codigo_acta":0,"grupo_id":"11435979","estado":0}]}